smvp/__init__.py
smvp/app.py
smvp/typed.py
smvp/utilities.py
smvp-0.2.14.dist-info/WHEEL
smvp-0.2.14.dist-info/entry_points.txt
smvp-0.2.14.dist-info/METADATA
smvp-0.2.14.dist-info/RECORD
