Metadata-Version: 2.3
Name: smvp
Version: 0.2.14
Summary: Send a formatted email from the command line
Keywords: ansi,cron,html,logs,mail,mime,python,scripting,send,sendmail,smvp
Author: Peter Nardi
Author-email: Peter Nardi <geozeke@gmail.com>
License: MIT License
Classifier: Development Status :: 4 - Beta
Classifier: Intended Audience :: Developers
Classifier: License :: OSI Approved :: MIT License
Classifier: Natural Language :: English
Classifier: Operating System :: POSIX :: Linux
Classifier: Operating System :: MacOS :: MacOS X
Classifier: Topic :: Utilities
Classifier: Topic :: System :: Logging
Classifier: Topic :: Text Processing :: Markup :: HTML
Classifier: Programming Language :: Python :: 3
Classifier: Programming Language :: Python :: 3.9
Classifier: Programming Language :: Python :: 3.10
Classifier: Programming Language :: Python :: 3.11
Classifier: Programming Language :: Python :: 3.12
Classifier: Programming Language :: Python :: 3.13
Requires-Dist: ansi2html>=1.9.2
Requires-Dist: bs4>=0.0.2
Requires-Dist: lxml>=5.3.0
Requires-Dist: tomli>=1.1.0 ; python_full_version < '3.11'
Requires-Python: >=3.9
Project-URL: Bug Tracker, https://github.com/geozeke/smvp/issues
Project-URL: Source Code, https://github.com/geozeke/smvp
